marwar_scraper/__about__.py
marwar_scraper/__init__.py
marwar_scraper/scrape.py
marginados_warc_scraper-1.0.1.dist-info/METADATA
marginados_warc_scraper-1.0.1.dist-info/WHEEL
marginados_warc_scraper-1.0.1.dist-info/entry_points.txt
marginados_warc_scraper-1.0.1.dist-info/licenses/LICENSE.txt
marginados_warc_scraper-1.0.1.dist-info/RECORD
