Metadata-Version: 2.1
Name: marginados-warc-scraper
Version: 1.0.1
Summary: Scrape Marginados data from a WARC file
Project-URL: Documentation, https://github.com/LeidenUniversityLibrary/marginados-warc-scraper#readme
Project-URL: Issues, https://github.com/LeidenUniversityLibrary/marginados-warc-scraper/issues
Project-URL: Source, https://github.com/LeidenUniversityLibrary/marginados-warc-scraper
Author-email: Ben Companjen <ben@companjen.name>
License-Expression: GPL-3.0-or-later
License-File: LICENSE.txt
Classifier: Development Status :: 4 - Beta
Classifier: Programming Language :: Python
Classifier: Programming Language :: Python :: 3.8
Classifier: Programming Language :: Python :: 3.9
Classifier: Programming Language :: Python :: 3.10
Classifier: Programming Language :: Python :: 3.11
Classifier: Programming Language :: Python :: Implementation :: CPython
Classifier: Programming Language :: Python :: Implementation :: PyPy
Requires-Python: >=3.8
Requires-Dist: beautifulsoup4
Requires-Dist: click
Requires-Dist: warcio
